{
    "backend": "flask",
    "db_name": "",
    "db_pass": "",
    "db_type": "sqlite",
    "db_user": "",
    "dbms": "1",
    "description": "generated product",
    "design": "adminator",
    "docker": "1",
    "err_code": 0,
    "frontend": "",
    "heroku": "0",
    "pattern": "mvc",
    "pro": "0",
    "task_id": "d091cddd-8baa-4835-9470-1f42cdd10343",
    "task_info": "Upload Sources [1%] - 78 files",
    "task_output": "d091cddd-8baa-4835-9470-1f42cdd10343.zip",
    "task_result": "SUCCESS",
    "task_state": "RUNNING",
    "task_ts_end": "2022-08-26-03-26-57",
    "task_ts_start": "2022-08-26-03-26-54"
}